aclcliextension/__init__.py
aclcliextension/cli.py
aclcliextension/dice.py
aclcliextension-1.0.0.dist-info/DESCRIPTION.rst
aclcliextension-1.0.0.dist-info/METADATA
aclcliextension-1.0.0.dist-info/RECORD
aclcliextension-1.0.0.dist-info/WHEEL
aclcliextension-1.0.0.dist-info/entry_points.txt
aclcliextension-1.0.0.dist-info/metadata.json
aclcliextension-1.0.0.dist-info/top_level.txt
