Metadata-Version: 2.0
Name: aclcliextension
Version: 1.0.0
Summary: Demo Package.
Home-page: UNKNOWN
Author: Vivek Subramaniam
Author-email: vivsubra@linkedin.com
License: MIT
Keywords: geeksforgeeks gfg article python package vibhu4agarwal
Platform: UNKNOWN
Classifier: Programming Language :: Python :: 3
Classifier: License :: OSI Approved :: MIT License
Classifier: Operating System :: OS Independent
